Workbook

Sheet 5 Selected Rows
A1: ContentAlchemy — 5 Selected Dataset Rows for A/B Testing
A2: Row # | B2: Product Category | C2: Product Name | D2: State | E2: Unit Price (INR) | F2: Review Rating | G2: Review Text | H2: Delivery Status
A3: 1 | B3: Home & Kitchen | C3: Cookware Set | D3: Maharashtra | E3: 12195.41 | F3: 5 | G3: Fantastic quality! | H3: Delivered
A4: 2 | B4: Home & Kitchen | C4: Cookware Set | D4: Sikkim | E4: 25574.41 | F4: 1 | G4: Waste of money | H4: Returned
A5: 3 | B5: Beauty | C5: Hair Dryer | D5: Telangana | E5: 19361.41 | F5: 5 | G5: Excellent product! | H5: Returned
A6: 4 | B6: Beauty | C6: Hair Dryer | D6: Tripura | E6: 46303.04 | F6: 2 | G6: Quality could improve | H6: Delivered
A7: 5 | B7: Electronics | C7: Headphones | D7: Assam | E7: 38145.72 | F7: 5 | G7: Highly recommend! | H7: Delivered

Sheet Prompt Library
A1: ContentAlchemy — Structured vs Generic Prompt Library
B2: Prompt Type
A3: 1 | B3: STRUCTURED | C3: Role: You are an expert Indian e-commerce copywriter for Amazon sales campaigns. Context: A customer in Maharashtra purchased a Cookware Set from Home & Kitchen for Rs.12,195. Rated 5/5. Said: 'Fantastic quality!' Order Delivered. Task: Write a compelling Instagram ad caption using this positive review as social proof. Include price and encourage purchase. Format: Hook line (1 punchy line) + Body (3-4 lines on features) + Social proof line (using review) + CTA. Include 2 emojis. Tone: Confident, trustworthy, aspirational, persuasive.
A4: 1 | B4: GENERIC | C4: Write an Instagram ad for a Cookware Set.
A5: 2 | B5: STRUCTURED | C5: Role: You are a senior brand reputation manager for an Indian e-commerce company. Context: Customer in Sikkim purchased Cookware Set for Rs.25,574. Order Returned. Rated 1/5. Said: 'Waste of money'. Task: Write a complete customer service email that (1) acknowledges concern with empathy, (2) offers full refund or free replacement, (3) highlights quality assurance, and (4) includes a recovery offer. Format: Email with greeting + 3 body paragraphs (acknowledgment, solution, recovery) + professional closing. Tone: Empathetic, professional, solution-focused.
A6: 2 | B6: GENERIC | C6: Respond to a bad review about a Cookware Set.
A7: 3 | B7: STRUCTURED | C7: Role: You are a top-tier Indian social media copywriter specialising in beauty products. Context: Customer in Telangana purchased Hair Dryer from Beauty for Rs.19,361. Rated 5/5. Said: 'Excellent product!' Task: Write a scroll-stopping Instagram ad caption with a strong hook, builds desire through features, uses review as social proof, closes with urgency and strong CTA. Format: Hook (1 line) + Body (4-5 lines) + Social proof + Urgency + CTA + 8-10 hashtags. Tone: Bold, aspirational, beauty-forward, exciting.
A8: 3 | B8: GENERIC | C8: Write an Instagram ad for a Hair Dryer.
A9: 4 | B9: STRUCTURED | C9: Role: You are a conversion-focused copywriter for an Indian beauty brand. Context: Customer in Tripura bought Hair Dryer for Rs.46,303. Delivered. Rated 2/5. Said: 'Quality could improve'. Task: Write a personalised outreach email that validates quality concern, explains premium features, offers exchange or free usage guide, includes loyalty discount. Format: Personalized greeting + 4 paragraphs (validation, features, offer, discount CTA) + warm closing. Tone: Understanding, helpful, premium, non-defensive.
A10: 4 | B10: GENERIC | C10: Write an email for a customer who gave a bad review for a Hair Dryer.
A11: 5 | B11: STRUCTURED | C11: Role: You are an expert Indian e-commerce copywriter specialising in electronics. Context: Customer in Assam purchased Headphones from Electronics for Rs.38,145. Rated 5/5. Said: 'Highly recommend!' Delivered. Task: Write a full Amazon product listing description highlighting audio features, using customer recommendation as social proof, targeting tech-savvy buyers. Format: Title hook + Overview (2 sentences) + 5 key features + Customer testimonial + Price value + Buy CTA. Tone: Technical, credible, aspirational, persuasive.
A12: 5 | B12: GENERIC | C12: Write a product description for Headphones.

Sheet AB Scoring Sheet
A1: ContentAlchemy — A/B Prompt Comparison and Scoring Sheet
A2: INPUT DATA | C2: PROMPT INFO | E2: OUTPUT | F2: SCORING — Enter 1 to 5 in each yellow cell | J2: RESULTS
A3: Row # | B3: Product | C3: Prompt Type | D3: Content Type | E3: Paste Copilot Output Here | F3: Contextual Accuracy (1-5) | G3: Sentiment Alignment (1-5) | H3: CTA Strength (1-5) | I3: Personaliz- ation (1-5) | J3: Average Score | K3: Winner (S or G)
A4: 1 | B4: Cookware Set | C4: STRUCTURED | D4: Instagram Caption | E4: Upgrade your kitchen in one smart move! 🔥 Premium cookware set with sturdy build & elegant finish Even heat distribution for perfectly cooked meals Durable, long‑lasting & super easy to clean All this at just Rs. 12,195—value that’s hard to beat 🍳 ⭐ 5/5 customer from Maharashtra says:“Fantastic quality!” Loved, rated, and delivered—don’t miss out! 👉 Tap to shop now on Amazon & cook like a pro. | F4: 5 | G4: 5 | H4: 5 | I4: 4 | J4: =IFERROR(AVERAGE(F4:I4),"") -> 4.75 | K4: s
A5: 1 | B5: Cookware Set | C5: GENERIC | D5: Instagram Caption | E5: Upgrade your kitchen with cookware that works as hard as you do. ✨ Even heat. ✨ Non‑stick ease. ✨ Built to last. From quick breakfasts to gourmet dinners — every meal feels effortless. Tap to upgrade your cooking game 🍳👇 | F5: 2 | G5: 3 | H5: 3 | I5: 1 | J5: =IFERROR(AVERAGE(F5:I5),"") -> 2.25 | K5: s
A6: 2 | B6: Cookware Set | C6: STRUCTURED | D6: Email Response | E6: **Subject:** We’re sorry about your experience — here’s how we’ll make it right Dear Customer, Thank you for taking the time to share your feedback. We’re truly sorry to hear that the cookware set you purchased did not meet your expectations and that the experience felt like a waste of money. We understand how disappointing this can be, especially for a premium purchase, and we sincerely regret the inconvenience caused to you in Sikkim. Your satisfaction is important to us. As a resolution, we would like to offer **a full refund of Rs. 25,574** to your original payment method, or **a free replacement** with a fresh quality‑checked unit—whichever you prefer. Please let us know your choice, and our support team will ensure the process is handled quickly and smoothly with no further effort required from your side. We also want to reassure you that this experience is not reflective of our usual standards. All our cookware goes through multiple quality assurance checks for materials, finish, and performance before dispatch. We are internally reviewing this case with our quality team to prevent similar issues in the future. As a gesture of goodwill and to regain your trust, we would like to offer you **a special recovery benefit**: an exclusive discount voucher for your next purchase, should you choose to shop with us again. We truly hope to have the opportunity to serve you better and deliver the quality experience you deserve. Thank you for your patience and understanding. Please feel free to reply to this email or contact our customer care team for immediate assistance. Warm regards, **Customer Experience Team** \[Company Name] \[Customer Support Contact Details] | F6: 5 | G6: 5 | H6: 4 | I6: 5 | J6: =IFERROR(AVERAGE(F6:I6),"") -> 4.75 | K6: s
A7: 2 | B7: Cookware Set | C7: GENERIC | D7: Email Response | E7: Thank you for sharing your feedback. We’re really sorry to hear that your experience with our cookware set didn’t meet expectations. That’s not the level of quality or performance we aim to deliver. We understand how frustrating kitchen issues can be, especially when you’re relying on cookware every day. Your comments help us improve, and we take them seriously. Please reach out to us at [support email / DM us] with your order details so our customer care team can assist you with a replacement, refund, or solution. We’d genuinely like the opportunity to make this right. Thank you for giving us a try — we appreciate your honesty. | F7: 2 | G7: 3 | H7: 2 | I7: 1 | J7: =IFERROR(AVERAGE(F7:I7),"") -> 2 | K7: s
A8: 3 | B8: Hair Dryer | C8: STRUCTURED | D8: Instagram Caption | E8: **Turn everyday hair days into salon‑level glam.** Engineered for fast drying with powerful airflow Advanced heat control to reduce frizz & protect shine Lightweight design for easy handling and smooth styling Perfect for sleek looks, soft waves, or quick touch‑ups Luxury performance worth every rupee at **Rs. 19,361** ⭐ **5/5 from a happy customer in Telangana:** *“Excellent product!”* ⚡ **Best‑sellers don’t stay in stock for long. Limited units available.** 👉 **Shop now & upgrade your hair game today.** \#HairGoals #BeautyMustHave #SalonAtHome #HairDryerLove #PremiumBeauty #IndianBeauty #GlossyHair #StyleUpgrade | F8: 5 | G8: 5 | H8: 5 | I8: 4 | J8: =IFERROR(AVERAGE(F8:I8),"") -> 4.75 | K8: s
A9: 3 | B9: Hair Dryer | C9: GENERIC | D9: Instagram Caption | E9: Salon‑Smooth Hair. Every Single Day. Meet the hair dryer that dries faster, styles better, and protects your shine. ✨ Powerful airflow ✨ Less heat damage ✨ Lightweight & easy to use Good hair days just got effortless. Tap to shine ✨👇 #HairGoals #StyleAtHome #HealthyHair | F9: 2 | G9: 3 | H9: 3 | I9: 1 | J9: =IFERROR(AVERAGE(F9:I9),"") -> 2.25 | K9: s
A10: 4 | B10: Hair Dryer | C10: STRUCTURED | D10: Email Campaign | E10: Subject: Thank you for your feedback — let us help you get the best experience Dear \[Customer Name], Thank you for sharing your honest feedback with us. We truly appreciate you taking the time to let us know that the quality of the hair dryer did not fully meet your expectations. For a premium purchase of **Rs. 46,303**, it’s completely understandable to expect excellence, and we’re sorry that your experience so far hasn’t reflected that. We’d also like to share a bit more about the product, as many of its premium benefits become noticeable with the right usage. This hair dryer is designed with advanced airflow technology, precise heat control, and long‑life internal components to support professional‑grade styling while protecting hair health. That said, we recognise that comfort, feel, and results can vary from person to person—and your feedback helps us improve. To support you better, we’d be happy to offer **a free exchange** for another unit, or alternatively, **a complimentary personalised usage guide** created by our product experts to help you get optimal performance based on your hair type and styling needs. Please do let us know which option you’d prefer—we want to make this effortless for you. As a thank‑you for giving us the opportunity to make things right, we’re also extending **an exclusive loyalty discount on your next purchase**, should you choose to continue with us. Simply reply to this email, and our team will arrange everything for you right away. Warm regards, Customer Care Team \[Brand Name] \[Support Email | Phone Number] | F10: 5 | G10: 4 | H10: 4 | I10: 5 | J10: =IFERROR(AVERAGE(F10:I10),"") -> 4.5 | K10: s
A11: 4 | B11: Hair Dryer | C11: GENERIC | D11: Email Campaign | E11: Subject: We’d Love to Make This Right Hi [Customer Name], We’re sorry to hear that you weren’t satisfied with your hair dryer. That’s not the experience we want you to have. We truly appreciate your feedback and would love the chance to help resolve this. Please reach out to us at [support email / phone] with your order details so we can assist you further. Thank you for giving us a try — we hope to turn this around for you. Best, [Brand Name] Team | F11: 1 | G11: 3 | H11: 2 | I11: 1 | J11: =IFERROR(AVERAGE(F11:I11),"") -> 1.75 | K11: s
A12: 5 | B12: Headphones | C12: STRUCTURED | D12: Product Description | E12: Experience Studio‑Grade Sound — Built for True Audio Enthusiasts Overview Designed for tech‑savvy listeners who demand precision, these premium headphones deliver immersive sound with exceptional clarity across all frequencies. Whether you’re streaming hi‑res music, gaming, or taking calls, every detail is engineered for performance and comfort. Key Features High‑Resolution Audio Drivers:** Tuned for deep bass, crisp mids, and ultra‑clear highs for an authentic soundstage Advanced Noise Isolation:** Minimises ambient noise so you can focus on pure audio Low‑Latency Performance:** Ideal for gaming and video—audio stays perfectly in sync Premium Build & Comfort:** Lightweight yet durable design with cushioned ear cups for long listening sessions Seamless Connectivity:** Stable, fast pairing with smartphones, laptops, and other devices What Customers Are Saying ⭐ 5/5 Rating | Verified Buyer from Assam** "Highly recommend!” — Praised for sound quality, comfort, and overall performance. Premium Sound, Smart Value Available now for Rs. 38,145, these headphones offer flagship‑level audio and build quality worthy of discerning users who won’t compromise. Buy Now** 👉 **Upgrade your listening experience today—order now on Amazon and hear the difference.** | F12: 5 | G12: 5 | H12: 5 | I12: 4 | J12: =IFERROR(AVERAGE(F12:I12),"") -> 4.75 | K12: s
A13: 5 | B13: Headphones | C13: GENERIC | D13: Product Description | E13: Premium Wireless Headphones Experience powerful sound and all‑day comfort with headphones designed for music lovers, gamers, and busy lifestyles alike. Crafted with advanced audio technology and a sleek, modern design, these headphones deliver immersive sound wherever you go. 🎧 Key Features Rich, Balanced Sound – Deep bass, clear mids, and crisp highs for an immersive listening experience Comfort Fit Design – Soft ear cushions and an adjustable headband for long listening sessions Wireless Convenience – Stable Bluetooth connectivity with extended range Long Battery Life – Enjoy hours of uninterrupted playback on a single charge Built‑in Microphone – Crystal‑clear calls and easy voice control Foldable & Lightweight – Perfect for travel, work, and everyday use 🔊 Designed for Every Moment Whether you're commuting, working out, gaming, or relaxing, these headphones provide exceptional sound quality and comfort without compromise. Upgrade your listening experience with headphones that combine performance, style, and reliability | F13: 2 | G13: 3 | H13: 3 | I13: 1 | J13: =IFERROR(AVERAGE(F13:I13),"") -> 2.25 | K13: s

Sheet Summary Dashboard
A1: ContentAlchemy — Prompt Effectiveness Summary Dashboard
A2: Scores auto-calculate from AB Scoring Sheet — fill in yellow cells first!
A3: Metric | B3: Structured Avg | C3: Generic Avg | D3: Difference | E3: Winner | F3: What It Measures
A4: Contextual Accuracy | B4: =IFERROR(AVERAGE('AB Scoring Sheet'!F4,'AB Scoring Sheet'!F6,'AB Scoring Sheet'!F8,'AB Scoring Sheet'!F10,'AB Scoring Sheet'!F12),"Fill scores first") -> 5 | C4: =IFERROR(AVERAGE('AB Scoring Sheet'!F5,'AB Scoring Sheet'!F7,'AB Scoring Sheet'!F9,'AB Scoring Sheet'!F11,'AB Scoring Sheet'!F13),"Fill scores first") -> 1.8 | D4: =IFERROR(B4-C4,"") -> 3.2 | E4: =IFERROR(IF(B4>C4,"STRUCTURED WINS","GENERIC WINS"),"") -> STRUCTURED WINS | F4: Does output mention correct product, price, and state?
A5: Sentiment Alignment | B5: =IFERROR(AVERAGE('AB Scoring Sheet'!G4,'AB Scoring Sheet'!G6,'AB Scoring Sheet'!G8,'AB Scoring Sheet'!G10,'AB Scoring Sheet'!G12),"Fill scores first") -> 4.8 | C5: =IFERROR(AVERAGE('AB Scoring Sheet'!G5,'AB Scoring Sheet'!G7,'AB Scoring Sheet'!G9,'AB Scoring Sheet'!G11,'AB Scoring Sheet'!G13),"Fill scores first") -> 3 | D5: =IFERROR(B5-C5,"") -> 1.8 | E5: =IFERROR(IF(B5>C5,"STRUCTURED WINS","GENERIC WINS"),"") -> STRUCTURED WINS | F5: Does the tone match the customer's review feeling?
A6: CTA Strength | B6: =IFERROR(AVERAGE('AB Scoring Sheet'!H4,'AB Scoring Sheet'!H6,'AB Scoring Sheet'!H8,'AB Scoring Sheet'!H10,'AB Scoring Sheet'!H12),"Fill scores first") -> 4.6 | C6: =IFERROR(AVERAGE('AB Scoring Sheet'!H5,'AB Scoring Sheet'!H7,'AB Scoring Sheet'!H9,'AB Scoring Sheet'!H11,'AB Scoring Sheet'!H13),"Fill scores first") -> 2.6 | D6: =IFERROR(B6-C6,"") -> 2 | E6: =IFERROR(IF(B6>C6,"STRUCTURED WINS","GENERIC WINS"),"") -> STRUCTURED WINS | F6: Is there a clear Buy Now or Shop Now call-to-action?
A7: Personalization | B7: =IFERROR(AVERAGE('AB Scoring Sheet'!I4,'AB Scoring Sheet'!I6,'AB Scoring Sheet'!I8,'AB Scoring Sheet'!I10,'AB Scoring Sheet'!I12),"Fill scores first") -> 4.4 | C7: =IFERROR(AVERAGE('AB Scoring Sheet'!I5,'AB Scoring Sheet'!I7,'AB Scoring Sheet'!I9,'AB Scoring Sheet'!I11,'AB Scoring Sheet'!I13),"Fill scores first") -> 1 | D7: =IFERROR(B7-C7,"") -> 3.4 | E7: =IFERROR(IF(B7>C7,"STRUCTURED WINS","GENERIC WINS"),"") -> STRUCTURED WINS | F7: Does it feel tailored to the region or customer persona?
A8: OVERALL SCORE | B8: =IFERROR(AVERAGE(B4:B7),"") -> 4.7 | C8: =IFERROR(AVERAGE(C4:C7),"") -> 2.1 | D8: =IFERROR(B8-C8,"") -> 2.6 | E8: =IFERROR(IF(B8>C8,"STRUCTURED WINS","GENERIC WINS"),"") -> STRUCTURED WINS | F8: Higher score = Structured prompts win overall
A10: SCORING GUIDE — How to score each output (1 = Poor to 5 = Excellent)
A11: Score 5 | C11: Perfect — mentions product, price, state, uses actual review text, has strong CTA
A12: Score 4 | C12: Good — most details present, CTA exists, tone mostly matches
A13: Score 3 | C13: Average — some details missing, weak CTA, tone partially right
A14: Score 2 | C14: Poor — generic copy, no personalization, no clear CTA
A15: Score 1 | C15: Very Poor — completely off-topic, irrelevant, or no meaningful output
